pnwkit/__init__.py
pnwkit/__init__.pyi
pnwkit/data.py
pnwkit/errors.py
pnwkit/new.py
pnwkit/py.typed
pnwkit/ratelimit.py
pnwkit/utils.py
pnwkit/ext/dumps/__init__.py
pnwkit/ext/dumps/__init__.pyi
pnwkit/ext/dumps/abc.py
pnwkit/ext/dumps/async_.py
pnwkit/ext/dumps/data.py
pnwkit/ext/dumps/sync.py
pnwkit/ext/scrape/__init__.py
pnwkit/ext/scrape/async_.py
pnwkit/ext/scrape/sync.py
pnwkit/legacy/async_.py
pnwkit/legacy/base.py
pnwkit/legacy/core.py
pnwkit/legacy/data.py
pnwkit/legacy/keys.py
pnwkit/legacy/paginator.py
pnwkit/legacy/sync.py
pnwkit_py-2.6.26.dist-info/LICENSE
pnwkit_py-2.6.26.dist-info/METADATA
pnwkit_py-2.6.26.dist-info/WHEEL
pnwkit_py-2.6.26.dist-info/top_level.txt
pnwkit_py-2.6.26.dist-info/RECORD
