Metadata-Version: 2.1
Name: pnwkit-py
Version: 2.6.26
Summary: A Python wrapper for the Politics and War API.
Home-page: https://github.com/Village05/pnwkit-py
Author: Village
License: MIT
Project-URL: Documentation, https://pnwkit-py.readthedocs.io/en/latest/
Project-URL: Issue tracker, https://github.com/Village05/pnwkit-py/issues
Classifier: Development Status :: 5 - Production/Stable
Classifier: License :: OSI Approved :: MIT License
Classifier: Intended Audience :: Developers
Classifier: Natural Language :: English
Classifier: Operating System :: OS Independent
Classifier: Programming Language :: Python :: 3.9
Classifier: Topic :: Internet
Classifier: Topic :: Software Development :: Libraries
Classifier: Topic :: Software Development :: Libraries :: Python Modules
Classifier: Topic :: Utilities
Requires-Python: >=3.8.0
License-File: LICENSE
Requires-Dist: aiohttp <3.9.0,>=3.7.0
Requires-Dist: requests <2.29.0,>=2.25.0
Requires-Dist: beautifulsoup4 <4.12.0,>=4.10.0
Provides-Extra: docs
Requires-Dist: sphinx ==4.0.3 ; extra == 'docs'
Requires-Dist: pydata-sphinx-theme ==0.6.3 ; extra == 'docs'
